aio_sf_streaming/__init__.py
aio_sf_streaming/__version__.py
aio_sf_streaming/connectors.py
aio_sf_streaming/core.py
aio_sf_streaming/mixins.py
tests/integration/__init__.py
tests/integration/test_basic.py
tests/unit/__init__.py
tests/unit/test_basic_api.py
tests/unit/test_connectors.py
tests/unit/test_mixins.py
tests/utils/__init__.py
tests/utils/async_itertools.py
tests/utils/async_tools.py
tests/utils/fake_server.py
aio_sf_streaming-0.3.7.dist-info/LICENSE
aio_sf_streaming-0.3.7.dist-info/METADATA
aio_sf_streaming-0.3.7.dist-info/WHEEL
aio_sf_streaming-0.3.7.dist-info/top_level.txt
aio_sf_streaming-0.3.7.dist-info/RECORD
