Metadata-Version: 2.1
Name: aio-sf-streaming
Version: 0.3.7
Summary: aio_sf_streaming is a simple Python 3.6 asyncio library allowing to connect and receive live notifications from Salesforce.
Home-page: https://github.com/papernest-public/aio_sf_streaming
Author: Christophe Gabard / papernest
Author-email: christophe.gabard@papernest.com
License: MIT
Keywords: asyncio aiohttp streaming saleforce push notification
Platform: UNKNOWN
Classifier: License :: OSI Approved :: MIT License
Classifier: Development Status :: 4 - Beta
Classifier: Programming Language :: Python
Classifier: Programming Language :: Python :: 3
Classifier: Programming Language :: Python :: 3.6
Classifier: Programming Language :: Python :: Implementation :: CPython
Requires-Python: >=3.6.0
Requires-Dist: aiohttp (<4,>=3)
Provides-Extra: docs
Requires-Dist: sphinx ; extra == 'docs'
Requires-Dist: sphinx-autobuild ; extra == 'docs'
Requires-Dist: sphinxcontrib-asyncio ; extra == 'docs'
Requires-Dist: sphinx-autodoc-typehints ; extra == 'docs'
Provides-Extra: tests
Requires-Dist: pytest (<4,>=3) ; extra == 'tests'
Requires-Dist: pytest-cov ; extra == 'tests'
Requires-Dist: pytest-asyncio ; extra == 'tests'
Requires-Dist: asynctest ; extra == 'tests'
Requires-Dist: coverage ; extra == 'tests'
